mkdocs_drawio_file/plugin.py
mkdocs_drawio_file-1.5.2.dist-info/METADATA
mkdocs_drawio_file-1.5.2.dist-info/WHEEL
mkdocs_drawio_file-1.5.2.dist-info/entry_points.txt
mkdocs_drawio_file-1.5.2.dist-info/RECORD
