Metadata-Version: 2.1
Name: mkdocs-drawio-file
Version: 1.5.2
Summary: Mkdocs plugin that renders .drawio files
Home-page: https://github.com/onixpro/mkdocs-drawio-file/
License: MIT
Keywords: mkdocs,plugin,markdown,drawio
Author: Sergey Lukin
Author-email: onixpro@gmail.com
Requires-Python: >=3.7.0,<4.0.0
Classifier: License :: OSI Approved :: MIT License
Classifier: Programming Language :: Python :: 3
Classifier: Programming Language :: Python :: 3.7
Classifier: Programming Language :: Python :: 3.8
Classifier: Programming Language :: Python :: 3.9
Classifier: Programming Language :: Python :: 3.10
Classifier: Programming Language :: Python :: 3.11
Requires-Dist: Jinja2 (>=3.0.3,<4.0.0)
Requires-Dist: beautifulsoup4 (>=4.11.0,<5.0.0)
Requires-Dist: lxml (>=4.9.0,<5.0.0)
Requires-Dist: mkdocs (>=1.4.0,<2.0.0)
Requires-Dist: requests (>=2.27.1,<3.0.0)
Project-URL: Repository, https://github.com/onixpro/mkdocs-drawio-file/
